dsa/__init__.py
dsa/hellodsa.py
dsa_stl/Balance_bst.py
dsa_stl/__init__.py
dsa_stl/directed_graph_stl.py
dsa_stl/dsu_stl.py
dsa_stl/graph_stl.py
dsa_stl/hellodsa.py
dsa_stl/lca_graph_stl.py
dsa_stl/testdsa.py
dsa_stl-0.0.7.dist-info/LICENSE
dsa_stl-0.0.7.dist-info/METADATA
dsa_stl-0.0.7.dist-info/WHEEL
dsa_stl-0.0.7.dist-info/top_level.txt
dsa_stl-0.0.7.dist-info/RECORD
